gunter/__init__.py
gunter/draw.py
gunter/index.py
gunter/merge.py
gunter/sheet.py
gunter/to_bdf.py
gunter/util/__init__.py
gunter/util/main.py
gunter-1.0.4.dist-info/LICENSE
gunter-1.0.4.dist-info/METADATA
gunter-1.0.4.dist-info/WHEEL
gunter-1.0.4.dist-info/entry_points.txt
gunter-1.0.4.dist-info/top_level.txt
gunter-1.0.4.dist-info/RECORD
