Metadata-Version: 2.2
Name: gunter
Version: 1.0.4
Summary: Program to turn any image of glyphs into a .hex-like format, and that into a .bdf
Author-email: sapero <sapero@icosahedr.online>
Project-URL: Homepage, https://git.icosahedr.online/sapero/gunter
Classifier: Programming Language :: Python :: 3
Classifier: License :: OSI Approved :: MIT License
Classifier: Operating System :: OS Independent
Requires-Python: >=3.9
License-File: LICENSE
Requires-Dist: pillow
